LICENSE
MANIFEST.in
README.md
configure_esp_secure_cert.py
requirements.txt
setup.py
esp_secure_cert/__init__.py
esp_secure_cert/configure_ds.py
esp_secure_cert/custflash_format.py
esp_secure_cert/efuse_helper.py
esp_secure_cert/esp_secure_cert_helper.py
esp_secure_cert/nvs_format.py
esp_secure_cert/tlv_format.py
esp_secure_cert/tlv_format_construct.py
esp_secure_cert/tlv_parser.py
esp_secure_cert_tool.egg-info/PKG-INFO
esp_secure_cert_tool.egg-info/SOURCES.txt
esp_secure_cert_tool.egg-info/dependency_links.txt
esp_secure_cert_tool.egg-info/requires.txt
esp_secure_cert_tool.egg-info/top_level.txt
tests/test_configure_esp_secure_cert.py
tests/test_tlv_parser.py