Metadata-Version: 2.1
Name: esp_secure_cert_tool
Version: 2.5.0
Summary: A python utility which helps to configure and provisionthe ESP platform with PKI credentials into the esp_secure_cert partition
Home-page: https://github.com/espressif/esp_secure_cert_mgr/blob/main/tools
Author: Espressif Systems
Author-email: 
License: Apache-2.0
Project-URL: Documentation, https://github.com/espressif/esp_secure_cert_mgr/blob/main/tools/README.md
Project-URL: Source, https://github.com/espressif/esp_secure_cert_mgr/blob/main/tools/configure_esp_secure_cert.py
Classifier: License :: OSI Approved :: Apache Software License
Classifier: Intended Audience :: Developers
Classifier: Natural Language :: English
Classifier: Operating System :: POSIX
Classifier: Operating System :: Microsoft :: Windows
Classifier: Operating System :: MacOS :: MacOS X
Classifier: Topic :: Software Development :: Embedded Systems
Classifier: Programming Language :: Python :: 3.8
Classifier: Programming Language :: Python :: 3.9
Classifier: Programming Language :: Python :: 3.10
Classifier: Programming Language :: Python :: 3.11
Classifier: Programming Language :: Python :: 3.12
Classifier: Programming Language :: Python :: 3.13
Requires-Python: >=3.8
License-File: LICENSE
Requires-Dist: cryptography
Requires-Dist: esptool
Requires-Dist: esp-idf-nvs-partition-gen<1.0.0,>=0.1.6
Requires-Dist: construct>=2.10.70
